README.txt
setup.cfg
setup.py
collective/__init__.py
collective.googlesystemstorage.egg-info/PKG-INFO
collective.googlesystemstorage.egg-info/SOURCES.txt
collective.googlesystemstorage.egg-info/dependency_links.txt
collective.googlesystemstorage.egg-info/entry_points.txt
collective.googlesystemstorage.egg-info/namespace_packages.txt
collective.googlesystemstorage.egg-info/not-zip-safe
collective.googlesystemstorage.egg-info/requires.txt
collective.googlesystemstorage.egg-info/top_level.txt
collective/googlesystemstorage/GData.py
collective/googlesystemstorage/GoogleSystemStorage.py
collective/googlesystemstorage/LICENSE
collective/googlesystemstorage/__init__.py
collective/googlesystemstorage/atct.zcml
collective/googlesystemstorage/configure.zcml
collective/googlesystemstorage/interfaces.py
collective/googlesystemstorage/meta.zcml
collective/googlesystemstorage/modifier.gif
collective/googlesystemstorage/zcml.py
docs/HISTORY.txt
docs/INSTALL.txt
docs/LICENSE.GPL
docs/LICENSE.txt