Metadata-Version: 1.0
Name: collective.googlesystemstorage
Version: 1.0.0
Summary: GSS saves the document types supported by the Google Docs service on the Google servers
Home-page: http://svn.plone.org/svn/collective/collective.googlesystemstorage/
Author: D'Elia Federica
Author-email: federica.delia@redturtle.it
License: GPL
Keywords: plone google googledocs iw.fss
Platform: UNKNOWN
Classifier: Framework :: Plone
Classifier: Programming Language :: Python
Classifier: Topic :: Software Development :: Libraries :: Python Modules
